dm_client/__init__.py
dm_client/biller/__init__.py
dm_client/biller/apps.py
dm_client/biller/service.py
dm_client/biller/tests/__init__.py
dm_client_biller-1.0.1.dist-info/licenses/LICENSE
dm_client_biller-1.0.1.dist-info/METADATA
dm_client_biller-1.0.1.dist-info/WHEEL
dm_client_biller-1.0.1.dist-info/top_level.txt
dm_client_biller-1.0.1.dist-info/RECORD
